sudoku-solve/__init__.py
sudoku-solve/sudoku.py
sudoku-solver/__init__.py
sudoku-solver/sudoku.py
sudoku_solve/__init__.py
sudoku_solve/sudoku.py
sudoku_solve-0.1.0.dist-info/LICENSE
sudoku_solve-0.1.0.dist-info/METADATA
sudoku_solve-0.1.0.dist-info/WHEEL
sudoku_solve-0.1.0.dist-info/entry_points.txt
sudoku_solve-0.1.0.dist-info/top_level.txt
sudoku_solve-0.1.0.dist-info/RECORD
