Metadata-Version: 2.1
Name: sudoku-solve
Version: 0.1.0
Summary: A small sudoku solver
Home-page: https://github.com/schuermannator/sudoku-solver
Author: Zach Schuermann
Author-email: zachary.schuermann@gmail.com
License: UNKNOWN
Platform: UNKNOWN
Classifier: Programming Language :: Python :: 3
Classifier: License :: OSI Approved :: GNU General Public License v3 (GPLv3)
Classifier: Operating System :: OS Independent
Requires-Dist: z3-solver
